setup.cfg
setup.py
src/xarray_events/EventsAccessor.py
src/xarray_events/__about__.py
src/xarray_events/__init__.py
src/xarray_events.egg-info/PKG-INFO
src/xarray_events.egg-info/SOURCES.txt
src/xarray_events.egg-info/dependency_links.txt
src/xarray_events.egg-info/requires.txt
src/xarray_events.egg-info/top_level.txt
src/xarray_events.egg-info/zip-safe