Metadata-Version: 2.1
Name: xarray-events
Version: 0.2.13
Summary: An open-source API for handling events based on xarray.
Home-page: https://github.com/teibit/xarray-events
Author: Ever García
Author-email: everalfonso.garcia01@estudiant.upf.edu
License: Apache 2.0
Download-URL: https://github.com/teibit/xarray-events/archive/v0.2.13.tar.gz
Keywords: numpy,pandas,xarray,events,python
Platform: UNKNOWN
Provides-Extra: tests
Provides-Extra: docs
